CHANGELOG.rst
LICENSE
MANIFEST.in
README.rst
pyproject.toml
setup.cfg
setup.py
tox.ini
.circleci/config.yml
.github/workflows/python-package.yml
Mopidy_Bookmarks.egg-info/PKG-INFO
Mopidy_Bookmarks.egg-info/SOURCES.txt
Mopidy_Bookmarks.egg-info/dependency_links.txt
Mopidy_Bookmarks.egg-info/entry_points.txt
Mopidy_Bookmarks.egg-info/not-zip-safe
Mopidy_Bookmarks.egg-info/requires.txt
Mopidy_Bookmarks.egg-info/top_level.txt
mopidy_bookmarks/__init__.py
mopidy_bookmarks/backend.py
mopidy_bookmarks/core.py
mopidy_bookmarks/ext.conf
mopidy_bookmarks/handlers.py
mopidy_bookmarks/utils.py
mopidy_bookmarks/controllers/__init__.py
mopidy_bookmarks/controllers/bookmarks.py
mopidy_bookmarks/controllers/generic.py
mopidy_bookmarks/controllers/store.py
tests/__init__.py
tests/conftest.py
tests/dummy_audio.py
tests/dummy_backend.py
tests/test_backend.py
tests/test_controller.py
tests/test_extension.py