Metadata-Version: 2.1
Name: Mopidy-Bookmarks
Version: 0.1.3
Summary: Provides bookmarks functionalities to mopidy.
Home-page: https://github.com/sapristi/mopidy-bookmarks
Author: Mathias Millet
Author-email: mathiasmillet@gmail.com
License: Apache License, Version 2.0
Platform: UNKNOWN
Classifier: Environment :: No Input/Output (Daemon)
Classifier: Intended Audience :: End Users/Desktop
Classifier: License :: OSI Approved :: Apache Software License
Classifier: Operating System :: OS Independent
Classifier: Programming Language :: Python :: 3
Classifier: Programming Language :: Python :: 3.7
Classifier: Programming Language :: Python :: 3.8
Classifier: Topic :: Multimedia :: Sound/Audio :: Players
Requires-Python: >=3.7
Provides-Extra: lint
Provides-Extra: release
Provides-Extra: test
Provides-Extra: dev
